pickpy/__init__.py
pickpy/keyboard.py
pickpy/main.py
pickpy/menu.py
pickpy/terminal.py
pickpy-0.1.1.dist-info/licenses/LICENSE
pickpy-0.1.1.dist-info/METADATA
pickpy-0.1.1.dist-info/WHEEL
pickpy-0.1.1.dist-info/top_level.txt
pickpy-0.1.1.dist-info/RECORD
