Metadata-Version: 2.4
Name: pickpy
Version: 0.1.1
Summary: Lightweight terminal menu library with TTY fallback and safe output
Author: pickpy authors
License-Expression: MIT
Project-URL: Homepage, https://github.com/fcaffaro/pickpy
Project-URL: Source, https://github.com/fcaffaro/pickpy
Project-URL: Issues, https://github.com/fcaffaro/pickpy/issues
Keywords: terminal,menu,tty,console,ansi
Classifier: Development Status :: 3 - Alpha
Classifier: Intended Audience :: Developers
Classifier: Environment :: Console
Classifier: Operating System :: Microsoft :: Windows
Classifier: Operating System :: POSIX :: Linux
Classifier: Programming Language :: Python :: 3
Classifier: Programming Language :: Python :: 3.10
Classifier: Programming Language :: Python :: 3.11
Classifier: Programming Language :: Python :: 3.12
Classifier: Programming Language :: Python :: 3.13
Classifier: Programming Language :: Python :: 3.14
Classifier: Topic :: Utilities
Classifier: Topic :: Terminals
Classifier: Topic :: Software Development :: Libraries
Requires-Python: >=3.10
License-File: LICENSE
Dynamic: license-file
